SafecastPy/__init__.py
SafecastPy/api.py
SafecastPy/endpoints.py
SafecastPy/exceptions.py
SafecastPy-0.1.1.dist-info/LICENSE
SafecastPy-0.1.1.dist-info/METADATA
SafecastPy-0.1.1.dist-info/WHEEL
SafecastPy-0.1.1.dist-info/top_level.txt
SafecastPy-0.1.1.dist-info/zip-safe
SafecastPy-0.1.1.dist-info/RECORD
