Metadata-Version: 2.1
Name: SafecastPy
Version: 0.1.1
Summary: A Python wrapper for the Safecast API.
Home-page: https://github.com/MonsieurV/SafecastPy
Author: Yoan Tournade
Author-email: yoan@ytotech.com
License: MIT
Platform: any
Requires-Dist: requests (>=2.9.1)
